vhcs/__init__.py
vhcs/ext/__init__.py
vhcs/ext/azure/__init__.py
vhcs/ext/azure/provider/__init__.py
vhcs/ext/azure/provider/_az_facade.py
vhcs/ext/azure/provider/_prepare.py
vhcs/ext/azure/provider/aad_group.py
vhcs/ext/azure/provider/aad_user.py
vhcs/ext/azure/provider/nat_gateway.py
vhcs/ext/azure/provider/nsg.py
vhcs/ext/azure/provider/public_ip.py
vhcs/ext/azure/provider/resource_group.py
vhcs/ext/azure/provider/storage_account_file.py
vhcs/ext/azure/provider/subnet.py
vhcs/ext/azure/provider/virtual_network.py
hcs_cli_ext_azure-0.1.176.dist-info/METADATA
hcs_cli_ext_azure-0.1.176.dist-info/WHEEL
hcs_cli_ext_azure-0.1.176.dist-info/top_level.txt
hcs_cli_ext_azure-0.1.176.dist-info/RECORD
