Metadata-Version: 2.1
Name: hcs-cli-ext-azure
Version: 0.1.176
Summary: Horizon Cloud Service CLI module.
Author-email: Nanw1103 <nanw1103@gmail.com>
Project-URL: Homepage, https://github.com/vmware/horizon-cloud-service-cli
Project-URL: Bug Tracker, https://github.com/vmware/horizon-cloud-service-cli/issues
Project-URL: documentation, https://readthedocs.org
Project-URL: repository, https://github.com/vmware/horizon-cloud-service-cli
Project-URL: changelog, https://github.com/vmware/horizon-cloud-service-cli/blob/main/CHANGELOG.md
Keywords: Horizon,Horizon Cloud,Horizon Cloud Service,CLI
Classifier: Programming Language :: Python :: 3
Classifier: Development Status :: 4 - Beta
Classifier: License :: OSI Approved :: MIT License
Classifier: Operating System :: OS Independent
Requires-Python: >=3.10
Requires-Dist: hcs-cli-core
Requires-Dist: msgraph-sdk
Requires-Dist: azure-mgmt-resource
Requires-Dist: azure-identity
Requires-Dist: azure-mgmt-network
Requires-Dist: azure-mgmt-msi
Requires-Dist: azure-mgmt-storage
Requires-Dist: azure-storage-file-share
Requires-Dist: azure-storage-blob
